Metadata-Version: 2.1
Name: AstroAtmosphere
Version: 1.3.1
Summary: Collection of equations for refractive index, refraction and dispersion calculations of atmospheric air.
Home-page: https://gitlab.astro-wise.org/micado/atmosphericmodel
Author: Joost van den Born
Author-email: born@astron.nl
License: GNU General Public License v3
Download-URL: https://gitlab.astro-wise.org/micado/atmosphericmodel/-/archive/v1.3.1/atmosphericmodel-v1.3.1.tar.gz
Keywords: REFRACTION,REFRACTIVITY,ATMOSPHERE,DISPERSION,CIDDOR
Platform: UNKNOWN
Classifier: Programming Language :: Python :: 3
Classifier: Operating System :: OS Independent
Classifier: Intended Audience :: Science/Research
Classifier: Topic :: Scientific/Engineering :: Astronomy
Provides-Extra: slalib
